[
    {
        "activationFunction": {
            "type": "heaviside",
            "x_shift": 0.0
        },
        "d_x": 1.0,
        "inputs": [
            [
                "gk 1",
                "output"
            ],
            [
                "nn 1",
                "output"
            ]
        ],
        "label": [
            1,
            "neural field"
        ],
        "restingLevel": -8.20100324764984,
        "tau": 101.9096919396565,
        "uniqueName": "nf 1",
        "x_max": 100
    },
    {
        "amplitude": 19.187620784310994,
        "amplitudeGlobal": -4.923193468050642,
        "circular": true,
        "d_x": 1.0,
        "inputs": [
            [
                "nf 1",
                "output"
            ]
        ],
        "label": [
            3,
            "gauss kernel"
        ],
        "normalized": true,
        "uniqueName": "gk 1",
        "width": 3.6488199418045966,
        "x_max": 100
    },
    {
        "amplitude": 0.2,
        "d_x": 1.0,
        "inputs": null,
        "label": [
            7,
            "normal noise"
        ],
        "uniqueName": "nn 1",
        "x_max": 100
    },
    {
        "activationFunction": {
            "type": "heaviside",
            "x_shift": 0.0
        },
        "d_x": 1.0,
        "inputs": [
            [
                "osck 2",
                "output"
            ],
            [
                "nn 2",
                "output"
            ]
        ],
        "label": [
            1,
            "neural field"
        ],
        "restingLevel": -8.815684137135984,
        "tau": 140.20271240850408,
        "uniqueName": "nf 2",
        "x_max": 100
    },
    {
        "amplitude": 1.5722221931476343,
        "amplitudeGlobal": -2.4085181665670112,
        "circular": true,
        "d_x": 1.0,
        "decay": 0.09278125357529089,
        "inputs": [
            [
                "nf 2",
                "output"
            ]
        ],
        "label": [
            5,
            "oscillatory kernel"
        ],
        "normalized": false,
        "uniqueName": "osck 2",
        "x_max": 100,
        "zeroCrossings": 0.9247063640448602
    },
    {
        "amplitude": 0.2,
        "d_x": 1.0,
        "inputs": null,
        "label": [
            7,
            "normal noise"
        ],
        "uniqueName": "nn 2",
        "x_max": 100
    },
    {
        "activationFunction": {
            "type": "heaviside",
            "x_shift": 0.0
        },
        "d_x": 1.0,
        "inputs": [
            [
                "mhk 3",
                "output"
            ],
            [
                "nn 3",
                "output"
            ]
        ],
        "label": [
            1,
            "neural field"
        ],
        "restingLevel": -1.9268886492563766,
        "tau": 112.78018421380762,
        "uniqueName": "nf 3",
        "x_max": 100
    },
    {
        "amplitudeExc": 5.819947864666168,
        "amplitudeGlobal": -4.283189751433664,
        "amplitudeInh": 19.967059765738057,
        "circular": true,
        "d_x": 1.0,
        "inputs": [
            [
                "nf 3",
                "output"
            ]
        ],
        "label": [
            4,
            "mexican hat kernel"
        ],
        "normalized": true,
        "uniqueName": "mhk 3",
        "widthExc": 7.817668742336252,
        "widthInh": 24.708883138664774,
        "x_max": 100
    },
    {
        "amplitude": 0.2,
        "d_x": 1.0,
        "inputs": null,
        "label": [
            7,
            "normal noise"
        ],
        "uniqueName": "nn 3",
        "x_max": 100
    }
]