[
    {
        "activationFunction": {
            "type": "heaviside",
            "x_shift": 0.0
        },
        "d_x": 1.0,
        "inputs": [
            [
                "mhk 1",
                "output"
            ],
            [
                "nn 1",
                "output"
            ]
        ],
        "label": [
            1,
            "neural field"
        ],
        "restingLevel": -4.534980412226519,
        "tau": 96.10879255895756,
        "uniqueName": "nf 1",
        "x_max": 100
    },
    {
        "amplitudeExc": 9.919698051695704,
        "amplitudeGlobal": -1.2556142567373745,
        "amplitudeInh": 15.46683776601935,
        "circular": true,
        "d_x": 1.0,
        "inputs": [
            [
                "nf 1",
                "output"
            ]
        ],
        "label": [
            4,
            "mexican hat kernel"
        ],
        "normalized": true,
        "uniqueName": "mhk 1",
        "widthExc": 1.651826544296296,
        "widthInh": 16.570606554128773,
        "x_max": 100
    },
    {
        "amplitude": 0.2,
        "d_x": 1.0,
        "inputs": null,
        "label": [
            7,
            "normal noise"
        ],
        "uniqueName": "nn 1",
        "x_max": 100
    },
    {
        "activationFunction": {
            "type": "heaviside",
            "x_shift": 0.0
        },
        "d_x": 1.0,
        "inputs": [
            [
                "osck 2",
                "output"
            ],
            [
                "nn 2",
                "output"
            ]
        ],
        "label": [
            1,
            "neural field"
        ],
        "restingLevel": -9.032780365115205,
        "tau": 47.69701473258568,
        "uniqueName": "nf 2",
        "x_max": 100
    },
    {
        "amplitude": 14.846386591768152,
        "amplitudeGlobal": -4.827652429287824,
        "circular": true,
        "d_x": 1.0,
        "decay": 0.2187989953602778,
        "inputs": [
            [
                "nf 2",
                "output"
            ]
        ],
        "label": [
            5,
            "oscillatory kernel"
        ],
        "normalized": false,
        "uniqueName": "osck 2",
        "x_max": 100,
        "zeroCrossings": 0.20675476080043545
    },
    {
        "amplitude": 0.2,
        "d_x": 1.0,
        "inputs": null,
        "label": [
            7,
            "normal noise"
        ],
        "uniqueName": "nn 2",
        "x_max": 100
    },
    {
        "activationFunction": {
            "type": "heaviside",
            "x_shift": 0.0
        },
        "d_x": 1.0,
        "inputs": [
            [
                "mhk 3",
                "output"
            ],
            [
                "nn 3",
                "output"
            ]
        ],
        "label": [
            1,
            "neural field"
        ],
        "restingLevel": -6.002252946744761,
        "tau": 53.942191652212415,
        "uniqueName": "nf 3",
        "x_max": 100
    },
    {
        "amplitudeExc": 12.176648169123496,
        "amplitudeGlobal": -3.4230217348136547,
        "amplitudeInh": 21.545902619028574,
        "circular": true,
        "d_x": 1.0,
        "inputs": [
            [
                "nf 3",
                "output"
            ]
        ],
        "label": [
            4,
            "mexican hat kernel"
        ],
        "normalized": true,
        "uniqueName": "mhk 3",
        "widthExc": 5.9035728211705285,
        "widthInh": 23.323068981551195,
        "x_max": 100
    },
    {
        "amplitude": 0.2,
        "d_x": 1.0,
        "inputs": null,
        "label": [
            7,
            "normal noise"
        ],
        "uniqueName": "nn 3",
        "x_max": 100
    }
]