[
    {
        "activationFunction": {
            "type": "heaviside",
            "x_shift": 0.0
        },
        "d_x": 1.0,
        "inputs": [
            [
                "gk 1",
                "output"
            ],
            [
                "nn 1",
                "output"
            ]
        ],
        "label": [
            1,
            "neural field"
        ],
        "restingLevel": -7.796505827177889,
        "tau": 141.10618210366087,
        "uniqueName": "nf 1",
        "x_max": 100
    },
    {
        "amplitude": 18.36886777609697,
        "amplitudeGlobal": -2.133119547454082,
        "circular": true,
        "d_x": 1.0,
        "inputs": [
            [
                "nf 1",
                "output"
            ]
        ],
        "label": [
            3,
            "gauss kernel"
        ],
        "normalized": true,
        "uniqueName": "gk 1",
        "width": 5.373742485772327,
        "x_max": 100
    },
    {
        "amplitude": 0.2,
        "d_x": 1.0,
        "inputs": null,
        "label": [
            7,
            "normal noise"
        ],
        "uniqueName": "nn 1",
        "x_max": 100
    },
    {
        "activationFunction": {
            "type": "heaviside",
            "x_shift": 0.0
        },
        "d_x": 1.0,
        "inputs": [
            [
                "gk 2",
                "output"
            ],
            [
                "nn 2",
                "output"
            ]
        ],
        "label": [
            1,
            "neural field"
        ],
        "restingLevel": -7.859243693076845,
        "tau": 142.80404229227958,
        "uniqueName": "nf 2",
        "x_max": 100
    },
    {
        "amplitude": 15.615308327208567,
        "amplitudeGlobal": -1.8920521524261211,
        "circular": true,
        "d_x": 1.0,
        "inputs": [
            [
                "nf 2",
                "output"
            ]
        ],
        "label": [
            3,
            "gauss kernel"
        ],
        "normalized": true,
        "uniqueName": "gk 2",
        "width": 9.698932876695114,
        "x_max": 100
    },
    {
        "amplitude": 0.2,
        "d_x": 1.0,
        "inputs": null,
        "label": [
            7,
            "normal noise"
        ],
        "uniqueName": "nn 2",
        "x_max": 100
    },
    {
        "activationFunction": {
            "type": "heaviside",
            "x_shift": 0.0
        },
        "d_x": 1.0,
        "inputs": [
            [
                "gk 3",
                "output"
            ],
            [
                "nn 3",
                "output"
            ]
        ],
        "label": [
            1,
            "neural field"
        ],
        "restingLevel": -17.64717162906995,
        "tau": 66.69519038890525,
        "uniqueName": "nf 3",
        "x_max": 100
    },
    {
        "amplitude": 15.65154179884437,
        "amplitudeGlobal": -2.9938411274216223,
        "circular": true,
        "d_x": 1.0,
        "inputs": [
            [
                "nf 3",
                "output"
            ]
        ],
        "label": [
            3,
            "gauss kernel"
        ],
        "normalized": true,
        "uniqueName": "gk 3",
        "width": 8.037042189739,
        "x_max": 100
    },
    {
        "amplitude": 0.2,
        "d_x": 1.0,
        "inputs": null,
        "label": [
            7,
            "normal noise"
        ],
        "uniqueName": "nn 3",
        "x_max": 100
    }
]