[
    {
        "activationFunction": {
            "type": "heaviside",
            "x_shift": 0.0
        },
        "d_x": 1.0,
        "inputs": [
            [
                "gk 1",
                "output"
            ],
            [
                "nn 1",
                "output"
            ]
        ],
        "label": [
            1,
            "neural field"
        ],
        "restingLevel": -2.282489911758951,
        "tau": 133.75493312605462,
        "uniqueName": "nf 1",
        "x_max": 100
    },
    {
        "amplitude": 6.204162760219446,
        "amplitudeGlobal": -0.8654907095107642,
        "circular": true,
        "d_x": 1.0,
        "inputs": [
            [
                "nf 1",
                "output"
            ]
        ],
        "label": [
            3,
            "gauss kernel"
        ],
        "normalized": true,
        "uniqueName": "gk 1",
        "width": 9.766624375270059,
        "x_max": 100
    },
    {
        "amplitude": 0.05,
        "d_x": 1.0,
        "inputs": null,
        "label": [
            7,
            "normal noise"
        ],
        "uniqueName": "nn 1",
        "x_max": 100
    },
    {
        "activationFunction": {
            "type": "heaviside",
            "x_shift": 0.0
        },
        "d_x": 1.0,
        "inputs": [
            [
                "gk 2",
                "output"
            ],
            [
                "nn 2",
                "output"
            ]
        ],
        "label": [
            1,
            "neural field"
        ],
        "restingLevel": -6.496471264487761,
        "tau": 19.566581239160868,
        "uniqueName": "nf 2",
        "x_max": 100
    },
    {
        "amplitude": 27.76510795868632,
        "amplitudeGlobal": -1.2347747352845722,
        "circular": true,
        "d_x": 1.0,
        "inputs": [
            [
                "nf 2",
                "output"
            ]
        ],
        "label": [
            3,
            "gauss kernel"
        ],
        "normalized": true,
        "uniqueName": "gk 2",
        "width": 5.264558747510586,
        "x_max": 100
    },
    {
        "amplitude": 0.05,
        "d_x": 1.0,
        "inputs": null,
        "label": [
            7,
            "normal noise"
        ],
        "uniqueName": "nn 2",
        "x_max": 100
    },
    {
        "activationFunction": {
            "type": "heaviside",
            "x_shift": 0.0
        },
        "d_x": 1.0,
        "inputs": [
            [
                "gk 3",
                "output"
            ],
            [
                "nn 3",
                "output"
            ]
        ],
        "label": [
            1,
            "neural field"
        ],
        "restingLevel": -3.2167181048514593,
        "tau": 64.64523878895527,
        "uniqueName": "nf 3",
        "x_max": 100
    },
    {
        "amplitude": 9.945749918160047,
        "amplitudeGlobal": -2.8866581130739237,
        "circular": true,
        "d_x": 1.0,
        "inputs": [
            [
                "nf 3",
                "output"
            ]
        ],
        "label": [
            3,
            "gauss kernel"
        ],
        "normalized": true,
        "uniqueName": "gk 3",
        "width": 7.479049154026036,
        "x_max": 100
    },
    {
        "amplitude": 0.05,
        "d_x": 1.0,
        "inputs": null,
        "label": [
            7,
            "normal noise"
        ],
        "uniqueName": "nn 3",
        "x_max": 100
    }
]