[
    {
        "activationFunction": {
            "type": "heaviside",
            "x_shift": 0.0
        },
        "d_x": 1.0,
        "inputs": [
            [
                "gk 1",
                "output"
            ]
        ],
        "label": [
            1,
            "neural field"
        ],
        "restingLevel": -11.252529522516838,
        "tau": 52.318918374116535,
        "uniqueName": "nf 1",
        "x_max": 100
    },
    {
        "amplitude": 6.781962349016448,
        "amplitudeGlobal": -0.07972798607447462,
        "circular": true,
        "d_x": 1.0,
        "inputs": [
            [
                "nf 1",
                "output"
            ]
        ],
        "label": [
            3,
            "gauss kernel"
        ],
        "normalized": true,
        "uniqueName": "gk 1",
        "width": 1.0827483215488478,
        "x_max": 100
    },
    {
        "activationFunction": {
            "type": "heaviside",
            "x_shift": 0.0
        },
        "d_x": 1.0,
        "inputs": [
            [
                "mhk 2",
                "output"
            ]
        ],
        "label": [
            1,
            "neural field"
        ],
        "restingLevel": -10.357397503980389,
        "tau": 250.49383208630616,
        "uniqueName": "nf 2",
        "x_max": 100
    },
    {
        "amplitudeExc": 22.44247363010285,
        "amplitudeGlobal": -0.018275515920495256,
        "amplitudeInh": 23.206503462668138,
        "circular": true,
        "d_x": 1.0,
        "inputs": [
            [
                "nf 2",
                "output"
            ]
        ],
        "label": [
            4,
            "mexican hat kernel"
        ],
        "normalized": true,
        "uniqueName": "mhk 2",
        "widthExc": 7.788726392421116,
        "widthInh": 12.426406494176593,
        "x_max": 100
    },
    {
        "activationFunction": {
            "type": "heaviside",
            "x_shift": 0.0
        },
        "d_x": 1.0,
        "inputs": [
            [
                "gk 3",
                "output"
            ],
            [
                "gk cg 1 - 3 581",
                "output"
            ]
        ],
        "label": [
            1,
            "neural field"
        ],
        "restingLevel": -4.507594041876491,
        "tau": 86.25554701509566,
        "uniqueName": "nf 3",
        "x_max": 100
    },
    {
        "amplitude": 1.4785111660539099,
        "amplitudeGlobal": -0.06737203545404652,
        "circular": true,
        "d_x": 1.0,
        "inputs": [
            [
                "nf 3",
                "output"
            ]
        ],
        "label": [
            3,
            "gauss kernel"
        ],
        "normalized": true,
        "uniqueName": "gk 3",
        "width": 3.4650753614407943,
        "x_max": 100
    },
    {
        "amplitude": 7.7648457474735055,
        "amplitudeGlobal": -0.06415953678777672,
        "circular": true,
        "d_x": 1.0,
        "inputs": [
            [
                "nf 1",
                "output"
            ]
        ],
        "label": [
            3,
            "gauss kernel"
        ],
        "normalized": true,
        "uniqueName": "gk cg 1 - 3 581",
        "width": 3.8566079493583048,
        "x_max": 100
    }
]