[
    {
        "activationFunction": {
            "type": "heaviside",
            "x_shift": 0.0
        },
        "d_x": 1.0,
        "inputs": [
            [
                "mhk 1",
                "output"
            ]
        ],
        "label": [
            1,
            "neural field"
        ],
        "restingLevel": -17.279734749612153,
        "tau": 167.6325910294249,
        "uniqueName": "nf 1",
        "x_max": 100
    },
    {
        "amplitudeExc": 10.36928004299029,
        "amplitudeGlobal": -0.029889275010932706,
        "amplitudeInh": 20.166443797991473,
        "circular": true,
        "d_x": 1.0,
        "inputs": [
            [
                "nf 1",
                "output"
            ]
        ],
        "label": [
            4,
            "mexican hat kernel"
        ],
        "normalized": true,
        "uniqueName": "mhk 1",
        "widthExc": 6.473940363169715,
        "widthInh": 5.90946086042773,
        "x_max": 100
    },
    {
        "activationFunction": {
            "type": "heaviside",
            "x_shift": 0.0
        },
        "d_x": 1.0,
        "inputs": [
            [
                "mhk 2",
                "output"
            ]
        ],
        "label": [
            1,
            "neural field"
        ],
        "restingLevel": -17.968435969127007,
        "tau": 16.42504855513618,
        "uniqueName": "nf 2",
        "x_max": 100
    },
    {
        "amplitudeExc": 24.904514161106892,
        "amplitudeGlobal": -0.015381717753122179,
        "amplitudeInh": 11.25897419049615,
        "circular": true,
        "d_x": 1.0,
        "inputs": [
            [
                "nf 2",
                "output"
            ]
        ],
        "label": [
            4,
            "mexican hat kernel"
        ],
        "normalized": true,
        "uniqueName": "mhk 2",
        "widthExc": 5.658308393061472,
        "widthInh": 15.624002262871725,
        "x_max": 100
    },
    {
        "activationFunction": {
            "type": "heaviside",
            "x_shift": 0.0
        },
        "d_x": 1.0,
        "inputs": [
            [
                "gk 3",
                "output"
            ],
            [
                "gk cg 2 - 3 234",
                "output"
            ]
        ],
        "label": [
            1,
            "neural field"
        ],
        "restingLevel": -3.1138403015291125,
        "tau": 192.39236642957755,
        "uniqueName": "nf 3",
        "x_max": 100
    },
    {
        "amplitude": 3.4759326828702517,
        "amplitudeGlobal": -0.0923672716540091,
        "circular": true,
        "d_x": 1.0,
        "inputs": [
            [
                "nf 3",
                "output"
            ]
        ],
        "label": [
            3,
            "gauss kernel"
        ],
        "normalized": true,
        "uniqueName": "gk 3",
        "width": 3.341263333133925,
        "x_max": 100
    },
    {
        "amplitude": 6.370897025465015,
        "amplitudeGlobal": -0.031294796890175794,
        "circular": true,
        "d_x": 1.0,
        "inputs": [
            [
                "nf 2",
                "output"
            ]
        ],
        "label": [
            3,
            "gauss kernel"
        ],
        "normalized": true,
        "uniqueName": "gk cg 2 - 3 234",
        "width": 3.7966710154927426,
        "x_max": 100
    }
]