[
    {
        "activationFunction": {
            "type": "heaviside",
            "x_shift": 0.0
        },
        "d_x": 1.0,
        "inputs": [
            [
                "mhk 1",
                "output"
            ],
            [
                "nn 1",
                "output"
            ]
        ],
        "label": [
            1,
            "neural field"
        ],
        "restingLevel": -14.726625547419989,
        "tau": 99.2317905387699,
        "uniqueName": "nf 1",
        "x_max": 100
    },
    {
        "amplitudeExc": 9.890963287720236,
        "amplitudeGlobal": -2.2294480681164943,
        "amplitudeInh": 23.15313625519725,
        "circular": true,
        "d_x": 1.0,
        "inputs": [
            [
                "nf 1",
                "output"
            ]
        ],
        "label": [
            4,
            "mexican hat kernel"
        ],
        "normalized": true,
        "uniqueName": "mhk 1",
        "widthExc": 7.136159904655324,
        "widthInh": 27.50434736088096,
        "x_max": 100
    },
    {
        "amplitude": 0.2,
        "d_x": 1.0,
        "inputs": null,
        "label": [
            7,
            "normal noise"
        ],
        "uniqueName": "nn 1",
        "x_max": 100
    },
    {
        "activationFunction": {
            "type": "heaviside",
            "x_shift": 0.0
        },
        "d_x": 1.0,
        "inputs": [
            [
                "osck 2",
                "output"
            ],
            [
                "nn 2",
                "output"
            ]
        ],
        "label": [
            1,
            "neural field"
        ],
        "restingLevel": -9.654318697265353,
        "tau": 164.35655879818592,
        "uniqueName": "nf 2",
        "x_max": 100
    },
    {
        "amplitude": 23.115539694328582,
        "amplitudeGlobal": -0.168866495324008,
        "circular": true,
        "d_x": 1.0,
        "decay": 0.2813715709659296,
        "inputs": [
            [
                "nf 2",
                "output"
            ]
        ],
        "label": [
            5,
            "oscillatory kernel"
        ],
        "normalized": false,
        "uniqueName": "osck 2",
        "x_max": 100,
        "zeroCrossings": 0.9878572478696173
    },
    {
        "amplitude": 0.2,
        "d_x": 1.0,
        "inputs": null,
        "label": [
            7,
            "normal noise"
        ],
        "uniqueName": "nn 2",
        "x_max": 100
    },
    {
        "activationFunction": {
            "type": "heaviside",
            "x_shift": 0.0
        },
        "d_x": 1.0,
        "inputs": [
            [
                "gk 3",
                "output"
            ],
            [
                "nn 3",
                "output"
            ]
        ],
        "label": [
            1,
            "neural field"
        ],
        "restingLevel": -13.269140547563538,
        "tau": 143.83069499247875,
        "uniqueName": "nf 3",
        "x_max": 100
    },
    {
        "amplitude": 7.167613610342221,
        "amplitudeGlobal": -0.2157530183078178,
        "circular": true,
        "d_x": 1.0,
        "inputs": [
            [
                "nf 3",
                "output"
            ]
        ],
        "label": [
            3,
            "gauss kernel"
        ],
        "normalized": true,
        "uniqueName": "gk 3",
        "width": 5.672201790176864,
        "x_max": 100
    },
    {
        "amplitude": 0.2,
        "d_x": 1.0,
        "inputs": null,
        "label": [
            7,
            "normal noise"
        ],
        "uniqueName": "nn 3",
        "x_max": 100
    }
]