[
    {
        "activationFunction": {
            "type": "heaviside",
            "x_shift": 0.0
        },
        "d_x": 1.0,
        "inputs": [
            [
                "gk 1",
                "output"
            ],
            [
                "nn 1",
                "output"
            ]
        ],
        "label": [
            1,
            "neural field"
        ],
        "restingLevel": -3.348191483836924,
        "tau": 165.50818500877503,
        "uniqueName": "nf 1",
        "x_max": 100
    },
    {
        "amplitude": 8.172204682748294,
        "amplitudeGlobal": -2.8599006556552777,
        "circular": true,
        "d_x": 1.0,
        "inputs": [
            [
                "nf 1",
                "output"
            ]
        ],
        "label": [
            3,
            "gauss kernel"
        ],
        "normalized": true,
        "uniqueName": "gk 1",
        "width": 7.931248767154532,
        "x_max": 100
    },
    {
        "amplitude": 0.2,
        "d_x": 1.0,
        "inputs": null,
        "label": [
            7,
            "normal noise"
        ],
        "uniqueName": "nn 1",
        "x_max": 100
    },
    {
        "activationFunction": {
            "type": "heaviside",
            "x_shift": 0.0
        },
        "d_x": 1.0,
        "inputs": [
            [
                "osck 2",
                "output"
            ],
            [
                "nn 2",
                "output"
            ]
        ],
        "label": [
            1,
            "neural field"
        ],
        "restingLevel": -8.619697385345178,
        "tau": 190.40397811686663,
        "uniqueName": "nf 2",
        "x_max": 100
    },
    {
        "amplitude": 1.316826126668425,
        "amplitudeGlobal": -3.5155978875185045,
        "circular": true,
        "d_x": 1.0,
        "decay": 0.0494766413090415,
        "inputs": [
            [
                "nf 2",
                "output"
            ]
        ],
        "label": [
            5,
            "oscillatory kernel"
        ],
        "normalized": false,
        "uniqueName": "osck 2",
        "x_max": 100,
        "zeroCrossings": 0.4166376521093108
    },
    {
        "amplitude": 0.2,
        "d_x": 1.0,
        "inputs": null,
        "label": [
            7,
            "normal noise"
        ],
        "uniqueName": "nn 2",
        "x_max": 100
    },
    {
        "activationFunction": {
            "type": "heaviside",
            "x_shift": 0.0
        },
        "d_x": 1.0,
        "inputs": [
            [
                "osck 3",
                "output"
            ],
            [
                "nn 3",
                "output"
            ]
        ],
        "label": [
            1,
            "neural field"
        ],
        "restingLevel": -9.252462119797885,
        "tau": 80.01110939283488,
        "uniqueName": "nf 3",
        "x_max": 100
    },
    {
        "amplitude": 9.10877235905447,
        "amplitudeGlobal": -3.6355656643183125,
        "circular": true,
        "d_x": 1.0,
        "decay": 0.24288089159127763,
        "inputs": [
            [
                "nf 3",
                "output"
            ]
        ],
        "label": [
            5,
            "oscillatory kernel"
        ],
        "normalized": false,
        "uniqueName": "osck 3",
        "x_max": 100,
        "zeroCrossings": 0.5419025930934149
    },
    {
        "amplitude": 0.2,
        "d_x": 1.0,
        "inputs": null,
        "label": [
            7,
            "normal noise"
        ],
        "uniqueName": "nn 3",
        "x_max": 100
    }
]