[
    {
        "activationFunction": {
            "type": "heaviside",
            "x_shift": 0.0
        },
        "d_x": 1.0,
        "inputs": [
            [
                "mhk 1",
                "output"
            ]
        ],
        "label": [
            1,
            "neural field"
        ],
        "restingLevel": -6.831676631632604,
        "tau": 85.74516976114289,
        "uniqueName": "nf 1",
        "x_max": 100
    },
    {
        "amplitudeExc": 9.0562251296407,
        "amplitudeGlobal": -0.05467368943376844,
        "amplitudeInh": 25.25406619414577,
        "circular": true,
        "d_x": 1.0,
        "inputs": [
            [
                "nf 1",
                "output"
            ]
        ],
        "label": [
            4,
            "mexican hat kernel"
        ],
        "normalized": true,
        "uniqueName": "mhk 1",
        "widthExc": 5.058279406811671,
        "widthInh": 24.196895657480518,
        "x_max": 100
    },
    {
        "activationFunction": {
            "type": "heaviside",
            "x_shift": 0.0
        },
        "d_x": 1.0,
        "inputs": [
            [
                "mhk 2",
                "output"
            ]
        ],
        "label": [
            1,
            "neural field"
        ],
        "restingLevel": -10.118447857689711,
        "tau": 163.8630948420007,
        "uniqueName": "nf 2",
        "x_max": 100
    },
    {
        "amplitudeExc": 8.457241573334308,
        "amplitudeGlobal": -0.06614777410081853,
        "amplitudeInh": 15.016874704344286,
        "circular": true,
        "d_x": 1.0,
        "inputs": [
            [
                "nf 2",
                "output"
            ]
        ],
        "label": [
            4,
            "mexican hat kernel"
        ],
        "normalized": true,
        "uniqueName": "mhk 2",
        "widthExc": 4.221942601094375,
        "widthInh": 18.754552739233446,
        "x_max": 100
    },
    {
        "activationFunction": {
            "type": "heaviside",
            "x_shift": 0.0
        },
        "d_x": 1.0,
        "inputs": [
            [
                "gk 3",
                "output"
            ],
            [
                "gk cg 2 - 3 162",
                "output"
            ]
        ],
        "label": [
            1,
            "neural field"
        ],
        "restingLevel": -4.3204795809592,
        "tau": 82.21327620784446,
        "uniqueName": "nf 3",
        "x_max": 100
    },
    {
        "amplitude": 2.2411953503885256,
        "amplitudeGlobal": -0.07092453254236024,
        "circular": true,
        "d_x": 1.0,
        "inputs": [
            [
                "nf 3",
                "output"
            ]
        ],
        "label": [
            3,
            "gauss kernel"
        ],
        "normalized": true,
        "uniqueName": "gk 3",
        "width": 3.495714443953134,
        "x_max": 100
    },
    {
        "amplitude": 3.8040187897071287,
        "amplitudeGlobal": -0.014004711416721966,
        "circular": true,
        "d_x": 1.0,
        "inputs": [
            [
                "nf 2",
                "output"
            ]
        ],
        "label": [
            3,
            "gauss kernel"
        ],
        "normalized": true,
        "uniqueName": "gk cg 2 - 3 162",
        "width": 4.197528566768004,
        "x_max": 100
    }
]