[
    {
        "activationFunction": {
            "type": "heaviside",
            "x_shift": 0.0
        },
        "d_x": 1.0,
        "inputs": [
            [
                "mhk 1",
                "output"
            ]
        ],
        "label": [
            1,
            "neural field"
        ],
        "restingLevel": -11.821035783538907,
        "tau": 82.58576132555554,
        "uniqueName": "nf 1",
        "x_max": 360
    },
    {
        "amplitudeExc": 21.920574538727394,
        "amplitudeGlobal": -0.10034270102884918,
        "amplitudeInh": 23.395943587791496,
        "circular": true,
        "d_x": 1.0,
        "inputs": [
            [
                "nf 1",
                "output"
            ]
        ],
        "label": [
            4,
            "mexican hat kernel"
        ],
        "normalized": true,
        "uniqueName": "mhk 1",
        "widthExc": 5.98772727070161,
        "widthInh": 15.789789029784604,
        "x_max": 360
    },
    {
        "activationFunction": {
            "type": "heaviside",
            "x_shift": 0.0
        },
        "d_x": 1.0,
        "inputs": [
            [
                "mhk 2",
                "output"
            ]
        ],
        "label": [
            1,
            "neural field"
        ],
        "restingLevel": -17.897953510830707,
        "tau": 249.52790300058297,
        "uniqueName": "nf 2",
        "x_max": 100
    },
    {
        "amplitudeExc": 15.24988840248744,
        "amplitudeGlobal": -0.32673706621500764,
        "amplitudeInh": 24.272712152353506,
        "circular": true,
        "d_x": 1.0,
        "inputs": [
            [
                "nf 2",
                "output"
            ]
        ],
        "label": [
            4,
            "mexican hat kernel"
        ],
        "normalized": true,
        "uniqueName": "mhk 2",
        "widthExc": 9.406153044051333,
        "widthInh": 7.8988999937615265,
        "x_max": 100
    }
]