[
    {
        "activationFunction": {
            "type": "heaviside",
            "x_shift": 0.0
        },
        "d_x": 1.0,
        "inputs": [
            [
                "mhk 1",
                "output"
            ],
            [
                "nn 1",
                "output"
            ]
        ],
        "label": [
            1,
            "neural field"
        ],
        "restingLevel": -14.472739047721875,
        "tau": 150.9786615627233,
        "uniqueName": "nf 1",
        "x_max": 100
    },
    {
        "amplitudeExc": 5.137250844270872,
        "amplitudeGlobal": -4.334965339339664,
        "amplitudeInh": 16.989808292889027,
        "circular": true,
        "d_x": 1.0,
        "inputs": [
            [
                "nf 1",
                "output"
            ]
        ],
        "label": [
            4,
            "mexican hat kernel"
        ],
        "normalized": true,
        "uniqueName": "mhk 1",
        "widthExc": 8.389371239600251,
        "widthInh": 23.832965662955583,
        "x_max": 100
    },
    {
        "amplitude": 0.2,
        "d_x": 1.0,
        "inputs": null,
        "label": [
            7,
            "normal noise"
        ],
        "uniqueName": "nn 1",
        "x_max": 100
    },
    {
        "activationFunction": {
            "type": "heaviside",
            "x_shift": 0.0
        },
        "d_x": 1.0,
        "inputs": [
            [
                "osck 2",
                "output"
            ],
            [
                "nn 2",
                "output"
            ]
        ],
        "label": [
            1,
            "neural field"
        ],
        "restingLevel": -9.24263265443449,
        "tau": 281.16884017339294,
        "uniqueName": "nf 2",
        "x_max": 100
    },
    {
        "amplitude": 7.923908896375595,
        "amplitudeGlobal": -3.0868459280423926,
        "circular": true,
        "d_x": 1.0,
        "decay": 0.7775679876933147,
        "inputs": [
            [
                "nf 2",
                "output"
            ]
        ],
        "label": [
            5,
            "oscillatory kernel"
        ],
        "normalized": false,
        "uniqueName": "osck 2",
        "x_max": 100,
        "zeroCrossings": 0.8546962865633753
    },
    {
        "amplitude": 0.2,
        "d_x": 1.0,
        "inputs": null,
        "label": [
            7,
            "normal noise"
        ],
        "uniqueName": "nn 2",
        "x_max": 100
    },
    {
        "activationFunction": {
            "type": "heaviside",
            "x_shift": 0.0
        },
        "d_x": 1.0,
        "inputs": [
            [
                "osck 3",
                "output"
            ],
            [
                "nn 3",
                "output"
            ]
        ],
        "label": [
            1,
            "neural field"
        ],
        "restingLevel": -5.367483849440465,
        "tau": 36.65395256658427,
        "uniqueName": "nf 3",
        "x_max": 100
    },
    {
        "amplitude": 20.55175846185172,
        "amplitudeGlobal": -0.4250551585134925,
        "circular": true,
        "d_x": 1.0,
        "decay": 0.9993999760956583,
        "inputs": [
            [
                "nf 3",
                "output"
            ]
        ],
        "label": [
            5,
            "oscillatory kernel"
        ],
        "normalized": false,
        "uniqueName": "osck 3",
        "x_max": 100,
        "zeroCrossings": 0.7011806871882861
    },
    {
        "amplitude": 0.2,
        "d_x": 1.0,
        "inputs": null,
        "label": [
            7,
            "normal noise"
        ],
        "uniqueName": "nn 3",
        "x_max": 100
    }
]