[
    {
        "activationFunction": {
            "type": "heaviside",
            "x_shift": 0.0
        },
        "d_x": 1.0,
        "inputs": [
            [
                "gk 1",
                "output"
            ]
        ],
        "label": [
            1,
            "neural field"
        ],
        "restingLevel": -10.316343191579861,
        "tau": 254.30662208122703,
        "uniqueName": "nf 1",
        "x_max": 100
    },
    {
        "amplitude": 1.7581029846427507,
        "amplitudeGlobal": -0.035620210477093545,
        "circular": true,
        "d_x": 1.0,
        "inputs": [
            [
                "nf 1",
                "output"
            ]
        ],
        "label": [
            3,
            "gauss kernel"
        ],
        "normalized": true,
        "uniqueName": "gk 1",
        "width": 3.248730611407136,
        "x_max": 100
    },
    {
        "activationFunction": {
            "type": "heaviside",
            "x_shift": 0.0
        },
        "d_x": 1.0,
        "inputs": [
            [
                "mhk 2",
                "output"
            ],
            [
                "gk cg 1 - 2 133",
                "output"
            ]
        ],
        "label": [
            1,
            "neural field"
        ],
        "restingLevel": -3.899258268775384,
        "tau": 29.476114322114583,
        "uniqueName": "nf 2",
        "x_max": 100
    },
    {
        "amplitudeExc": 20.970027999537404,
        "amplitudeGlobal": -0.010199585008175097,
        "amplitudeInh": 27.901929262032123,
        "circular": true,
        "d_x": 1.0,
        "inputs": [
            [
                "nf 2",
                "output"
            ]
        ],
        "label": [
            4,
            "mexican hat kernel"
        ],
        "normalized": true,
        "uniqueName": "mhk 2",
        "widthExc": 4.416407741842486,
        "widthInh": 6.277464928389069,
        "x_max": 100
    },
    {
        "amplitude": 5.482277890709132,
        "amplitudeGlobal": -0.05456201738315876,
        "circular": true,
        "d_x": 1.0,
        "inputs": [
            [
                "nf 1",
                "output"
            ]
        ],
        "label": [
            3,
            "gauss kernel"
        ],
        "normalized": true,
        "uniqueName": "gk cg 1 - 2 133",
        "width": 2.4266983278945604,
        "x_max": 100
    }
]