[
    {
        "activationFunction": {
            "type": "heaviside",
            "x_shift": 0.0
        },
        "d_x": 1.0,
        "inputs": [
            [
                "gk 1",
                "output"
            ]
        ],
        "label": [
            1,
            "neural field"
        ],
        "restingLevel": -11.947169250904492,
        "tau": 76.70849370666056,
        "uniqueName": "nf 1",
        "x_max": 100
    },
    {
        "amplitude": 6.860115754960697,
        "amplitudeGlobal": -0.03338096142433017,
        "circular": true,
        "d_x": 1.0,
        "inputs": [
            [
                "nf 1",
                "output"
            ]
        ],
        "label": [
            3,
            "gauss kernel"
        ],
        "normalized": true,
        "uniqueName": "gk 1",
        "width": 3.0155240277769804,
        "x_max": 100
    },
    {
        "activationFunction": {
            "type": "heaviside",
            "x_shift": 0.0
        },
        "d_x": 1.0,
        "inputs": [
            [
                "mhk 2",
                "output"
            ],
            [
                "gk cg 1 - 2 551",
                "output"
            ],
            [
                "gk cg 3 - 2 865",
                "output"
            ]
        ],
        "label": [
            1,
            "neural field"
        ],
        "restingLevel": -3.962426411800706,
        "tau": 99.76723015200687,
        "uniqueName": "nf 2",
        "x_max": 100
    },
    {
        "amplitudeExc": 13.523272482335972,
        "amplitudeGlobal": -0.04766999932822983,
        "amplitudeInh": 20.354343368660047,
        "circular": true,
        "d_x": 1.0,
        "inputs": [
            [
                "nf 2",
                "output"
            ]
        ],
        "label": [
            4,
            "mexican hat kernel"
        ],
        "normalized": true,
        "uniqueName": "mhk 2",
        "widthExc": 6.066209077234566,
        "widthInh": 11.94855862402368,
        "x_max": 100
    },
    {
        "activationFunction": {
            "type": "heaviside",
            "x_shift": 0.0
        },
        "d_x": 1.0,
        "inputs": [
            [
                "mhk 3",
                "output"
            ],
            [
                "gk cg 1 - 3 864",
                "output"
            ]
        ],
        "label": [
            1,
            "neural field"
        ],
        "restingLevel": -7.083355807708765,
        "tau": 160.1376823327483,
        "uniqueName": "nf 3",
        "x_max": 100
    },
    {
        "amplitudeExc": 22.70863592805493,
        "amplitudeGlobal": -0.019821256293198045,
        "amplitudeInh": 26.716306141473126,
        "circular": true,
        "d_x": 1.0,
        "inputs": [
            [
                "nf 3",
                "output"
            ]
        ],
        "label": [
            4,
            "mexican hat kernel"
        ],
        "normalized": true,
        "uniqueName": "mhk 3",
        "widthExc": 3.843176978919009,
        "widthInh": 26.839657749969977,
        "x_max": 100
    },
    {
        "amplitude": 7.440908350765898,
        "amplitudeGlobal": -0.06360407650862732,
        "circular": true,
        "d_x": 1.0,
        "inputs": [
            [
                "nf 1",
                "output"
            ]
        ],
        "label": [
            3,
            "gauss kernel"
        ],
        "normalized": true,
        "uniqueName": "gk cg 1 - 2 551",
        "width": 3.2440209944147496,
        "x_max": 100
    },
    {
        "amplitude": 1.0,
        "amplitudeGlobal": -0.1,
        "circular": true,
        "d_x": 1.0,
        "inputs": [
            [
                "nf 1",
                "output"
            ]
        ],
        "label": [
            3,
            "gauss kernel"
        ],
        "normalized": true,
        "uniqueName": "gk cg 1 - 3 864",
        "width": 1.0,
        "x_max": 100
    },
    {
        "amplitude": 7.440908350765898,
        "amplitudeGlobal": -0.06360407650862732,
        "circular": true,
        "d_x": 1.0,
        "inputs": [
            [
                "nf 3",
                "output"
            ]
        ],
        "label": [
            3,
            "gauss kernel"
        ],
        "normalized": true,
        "uniqueName": "gk cg 3 - 2 865",
        "width": 3.2440209944147496,
        "x_max": 100
    }
]